mylib003/__init__.py
mylib003-0.1.dist-info/LICENSE.txt
mylib003-0.1.dist-info/METADATA
mylib003-0.1.dist-info/WHEEL
mylib003-0.1.dist-info/top_level.txt
mylib003-0.1.dist-info/RECORD
