Metadata-Version: 2.1
Name: mylib003
Version: 0.1
Summary: for addition of two numbers
Author: Ajay Bhosale
Author-email: ajaybhosale852@gmail.com
Classifier: Programming Language :: Python :: 3
Classifier: License :: OSI Approved :: MIT License
Classifier: Operating System :: OS Independent
License-File: LICENSE.txt
